demicode/__init__.py
demicode/__main__.py
demicode/benchmark.py
demicode/display.py
demicode/py.typed
demicode/selection.py
demicode/statistics.py
demicode/tool.py
demicode/db/_property.py
demicode/db/codegen.py
demicode/db/codepoint.py
demicode/db/mirror.py
demicode/db/model.py
demicode/db/parser.py
demicode/db/ucd.py
demicode/db/version.py
demicode/ui/action.py
demicode/ui/control.py
demicode/ui/darkmode.py
demicode/ui/render.py
demicode/ui/terminal.py
demicode/ui/termio.py
demicode/util/image.py
demicode-1.7.0.dist-info/entry_points.txt
demicode-1.7.0.dist-info/LICENSE
demicode-1.7.0.dist-info/WHEEL
demicode-1.7.0.dist-info/METADATA
demicode-1.7.0.dist-info/RECORD
