Metadata-Version: 2.1
Name: demicode
Version: 1.7.0
Summary: Fixed-width display of Unicode is deeply broken
Keywords: Unicode,fixed-width,East Asian width,wcwidth,hot mess
Author-email: Robert Grimm <rgrimm@alum.mit.edu>
Requires-Python: >=3.11
Requires-Dist: Pillow ; extra == "bench"
Requires-Dist: pyright ; extra == "dev"
Requires-Dist: flit ; extra == "dev"
Project-URL: repository, https://github.com/apparebit/demicode
Provides-Extra: bench
Provides-Extra: dev
